smart_inputs/__init__.py
smart_inputs/smart_inputs.py
smart_inputs-0.3.1.dist-info/WHEEL
smart_inputs-0.3.1.dist-info/METADATA
smart_inputs-0.3.1.dist-info/LICENSE
smart_inputs-0.3.1.dist-info/RECORD
