Metadata-Version: 2.1
Name: smart_inputs
Version: 0.3.1
Summary: Smarter Inputs for easier to read python
License: MIT
Author-email: fanoway <86997883+fanoway@users.noreply.github.com>
Requires-Python: >=3.8
Requires-Dist: sphinx-rtd-theme>=1.0.0
Project-URL: homepage, https://github.com/fanoway/smart_inputs
